octopus_sensing/OpenVibe/csv2edf.xml
octopus_sensing/OpenVibe/display-save-eeg-exp2.xml
octopus_sensing/OpenVibe/display-save-eeg.xml
octopus_sensing/__init__.py
octopus_sensing/common/__init__.py
octopus_sensing/common/endpoint_base.py
octopus_sensing/common/message.py
octopus_sensing/common/message_creators.py
octopus_sensing/device_coordinator.py
octopus_sensing/device_message_endpoint.py
octopus_sensing/devices/__init__.py
octopus_sensing/devices/audio_streaming.py
octopus_sensing/devices/brainflow_openbci_streaming.py
octopus_sensing/devices/brainflow_streaming.py
octopus_sensing/devices/camera_streaming.py
octopus_sensing/devices/common.py
octopus_sensing/devices/device.py
octopus_sensing/devices/lsl_streaming.py
octopus_sensing/devices/network_devices/http_device.py
octopus_sensing/devices/network_devices/socket_device.py
octopus_sensing/devices/open_vibe_streaming.py
octopus_sensing/devices/openbci_streaming.py
octopus_sensing/devices/realtime_data_device.py
octopus_sensing/devices/shimmer3_streaming.py
octopus_sensing/devices/testdevice_streaming.py
octopus_sensing/devices/tobiiglasses_streaming.py
octopus_sensing/preprocessing/__init__.py
octopus_sensing/preprocessing/audiovideo_split.py
octopus_sensing/preprocessing/openbci.py
octopus_sensing/preprocessing/openbci_brainflow.py
octopus_sensing/preprocessing/preprocess_devices.py
octopus_sensing/preprocessing/shimmer3.py
octopus_sensing/preprocessing/utils.py
octopus_sensing/questionnaire/__init__.py
octopus_sensing/questionnaire/opinion_question.py
octopus_sensing/questionnaire/question.py
octopus_sensing/questionnaire/questionnaire.py
octopus_sensing/questionnaire/text_question.py
octopus_sensing/realtime_data_endpoint.py
octopus_sensing/stimuli/__init__.py
octopus_sensing/stimuli/image_stimulus.py
octopus_sensing/stimuli/stimulus.py
octopus_sensing/stimuli/video_stimulus.py
octopus_sensing/tests/__init__.py
octopus_sensing/tests/data/preprocess_expected/OpenBCI_16_continuous/OpenBCI-20-cont16-00.csv
octopus_sensing-4.4.5.dist-info/LICENSE
octopus_sensing-4.4.5.dist-info/METADATA
octopus_sensing-4.4.5.dist-info/WHEEL
octopus_sensing-4.4.5.dist-info/RECORD
