Metadata-Version: 2.1
Name: octopus-sensing
Version: 4.4.5
Summary: Library for recording data synchronously from different physiological sensors
Home-page: https://octopus-sensing.nastaran-saffar.me
License: GPL-3.0-or-later
Keywords: sensors,eeg,gsr,recorder
Author: Nastaran Saffaryazdi
Author-email: nsaffar@gmail.com
Requires-Python: >=3.10,<3.13
Classifier: License :: OSI Approved :: GNU General Public License v3 or later (GPLv3+)
Classifier: Programming Language :: Python :: 3
Classifier: Programming Language :: Python :: 3.10
Classifier: Programming Language :: Python :: 3.11
Classifier: Programming Language :: Python :: 3.12
Requires-Dist: PyGObject (==3.40.1) ; sys_platform != "win32"
Requires-Dist: bitstring (>=3.1.7,<4.0.0)
Requires-Dist: bluepy (==1.3.0) ; sys_platform == "linux"
Requires-Dist: brainflow (==4.9.3)
Requires-Dist: heartpy (==1.2.7)
Requires-Dist: libtobiiglassesctrl (==2.4.3)
Requires-Dist: miniaudio (==1.61)
Requires-Dist: mne (==0.23.4)
Requires-Dist: msgpack (==1.1.0)
Requires-Dist: numpy (==1.26.4)
Requires-Dist: opencv-python (==4.10.0.84)
Requires-Dist: pandas (==2.2.3)
Requires-Dist: pyOpenBCI (==0.13)
Requires-Dist: pyasyncore (==1.0.4)
Requires-Dist: pydub (==0.25.1)
Requires-Dist: pylsl (==1.16.2)
Requires-Dist: pyserial (==3.5)
Requires-Dist: requests (==2.32.3)
Requires-Dist: scipy (==1.14.1)
Requires-Dist: screeninfo (==0.7)
Requires-Dist: setuptools (==75.6.0)
Requires-Dist: sounddevice (==0.4.7)
Requires-Dist: xmltodict (==0.12.0)
Project-URL: Repository, https://github.com/octopus-sensing/octopus-sensing
